{
  "companyName" : "Weird Deals Gazette",
  "headOffice" : "Esanbe Hanakita Kojima",
  "established" : 1818, 
  "weirdDeals" : [
    {
      "name" : "Nothing", 
      "description" : "What do you get for the person who has everything? Nothing — literally. But unlike traditional nothing, this one will cost you almost $7. It comes in different colors so hurry before supplies last.",
      "price" : "$6.98", 
      "options" : [
        "Blue nothing", 
        "White nothing", 
        "Green nothing" 
      ],
      "image" : "nothing.jpg"
    },

    {
      "name" : "30 pieces of fake garlic", 
      "description" : "Take decorating with fake stuff to the next level with these fake garlic knobs. Get these and your kitchen will never look the same again.",
      "price" : "$10.99", 
      "options" : [
        "White basket", 
        "Grey basket", 
        "Orange basket" 
      ],
      "image": "garlic.jpg"
    },

    {
      "name" : "A horror movie sound maker",
      "description" : "Surprise guests by making them think IT is hiding just around the corner. You can make your own mimics too.",
      "price" : "$299.00", 
      "options" : [
        "Get out", 
        "A quiet place", 
        "Psycho"     
      ],
      "image" : "sound.jpg"
    },

    {
      "name" : "A pizza hut", 
      "description" : "Indulge in everyone's life-long desire of wearing pizza atop their head. Beware of the sprinkled parmesan as you nod or shake your head, though — some might mistake it for dandruff.",
      "price" : "$11.62", 
      "options" : [
        "Cheddar cheese", 
        "Parmesan cheese", 
        "Mozzarella cheese" 
      ],
      "image": "pizzahut.jpg"
    },

    {
      "name" : "A USB fridge", 
      "description" : "Enjoy a cold one with one, single refrigerated beverage at your fingertips. No driver needed. Will work with any PC or Macintosh. Top selling colors are:",
      "price" : "$38.00", 
      "options" : [
        "Red", 
        "Silver", 
        "Yellow" 
      ],
      "image": "fridge.jpg"
    }
  ]
}